lava/lib/dl/bootstrap/README.md
lava/lib/dl/bootstrap/__init__.py
lava/lib/dl/bootstrap/ann_sampler.py
lava/lib/dl/bootstrap/block/__init__.py
lava/lib/dl/bootstrap/block/base.py
lava/lib/dl/bootstrap/block/cuba.py
lava/lib/dl/bootstrap/routine.py
lava/lib/dl/netx/README.md
lava/lib/dl/netx/__init__.py
lava/lib/dl/netx/blocks/__init__.py
lava/lib/dl/netx/blocks/models.py
lava/lib/dl/netx/blocks/process.py
lava/lib/dl/netx/hdf5.py
lava/lib/dl/netx/sequential_modules.py
lava/lib/dl/netx/utils.py
lava/lib/dl/slayer/README.md
lava/lib/dl/slayer/__init__.py
lava/lib/dl/slayer/auto.py
lava/lib/dl/slayer/axon/__init__.py
lava/lib/dl/slayer/axon/delay.py
lava/lib/dl/slayer/axon/delta.py
lava/lib/dl/slayer/block/__init__.py
lava/lib/dl/slayer/block/adrf.py
lava/lib/dl/slayer/block/adrf_iz.py
lava/lib/dl/slayer/block/alif.py
lava/lib/dl/slayer/block/base.py
lava/lib/dl/slayer/block/cuba.py
lava/lib/dl/slayer/block/rf.py
lava/lib/dl/slayer/block/rf_iz.py
lava/lib/dl/slayer/block/sigma_delta.py
lava/lib/dl/slayer/classifier.py
lava/lib/dl/slayer/dendrite/__init__.py
lava/lib/dl/slayer/dendrite/sigma.py
lava/lib/dl/slayer/io.py
lava/lib/dl/slayer/jitconfig.py
lava/lib/dl/slayer/loss.py
lava/lib/dl/slayer/neuron/__init__.py
lava/lib/dl/slayer/neuron/adrf.py
lava/lib/dl/slayer/neuron/adrf_iz.py
lava/lib/dl/slayer/neuron/alif.py
lava/lib/dl/slayer/neuron/base.py
lava/lib/dl/slayer/neuron/cuba.py
lava/lib/dl/slayer/neuron/dropout.py
lava/lib/dl/slayer/neuron/dynamics/__init__.py
lava/lib/dl/slayer/neuron/dynamics/adaptive_phase_th.cu
lava/lib/dl/slayer/neuron/dynamics/adaptive_phase_th.py
lava/lib/dl/slayer/neuron/dynamics/adaptive_resonator.cu
lava/lib/dl/slayer/neuron/dynamics/adaptive_resonator.py
lava/lib/dl/slayer/neuron/dynamics/adaptive_threshold.cu
lava/lib/dl/slayer/neuron/dynamics/adaptive_threshold.py
lava/lib/dl/slayer/neuron/dynamics/leaky_integrator.cu
lava/lib/dl/slayer/neuron/dynamics/leaky_integrator.py
lava/lib/dl/slayer/neuron/dynamics/resonator.cu
lava_dl-0.6.0.dist-info/LICENSE
lava_dl-0.6.0.dist-info/METADATA
lava_dl-0.6.0.dist-info/WHEEL
lava_dl-0.6.0.dist-info/RECORD
